serverless_models_db/__init__.py
serverless_models_db/db/__init__.py
serverless_models_db/db/model/__init__.py
serverless_models_db/db/model/base_model.py
serverless_models_db/db/model/domain.py
serverless_models_db/db/model/function/__init__.py
serverless_models_db/db/model/function/function.py
serverless_models_db/db/model/function/tag.py
serverless_models_db/db/model/log.py
serverless_models_db/db/model/trigger/__init__.py
serverless_models_db/db/model/trigger/trigger.py
serverless_models_db/db/model/trigger/type.py
serverless_models_db/db/model/user/__init__.py
serverless_models_db/db/model/user/role.py
serverless_models_db/db/model/user/script_way.py
serverless_models_db/db/model/user/user.py
serverless_models_db/db/session.py
serverless_models_db/dto/__init__.py
serverless_models_db/dto/base.py
serverless_models_db/dto/domain.py
serverless_models_db/dto/function/__init__.py
serverless_models_db/dto/function/function.py
serverless_models_db/dto/function/tag.py
serverless_models_db/dto/log.py
serverless_models_db/dto/trigger/__init__.py
serverless_models_db/dto/trigger/trigger.py
serverless_models_db/dto/trigger/type.py
serverless_models_db/dto/user/__init__.py
serverless_models_db/dto/user/role.py
serverless_models_db/dto/user/script_way.py
serverless_models_db/dto/user/user.py
serverless_models_db-0.0.3.dist-info/METADATA
serverless_models_db-0.0.3.dist-info/WHEEL
serverless_models_db-0.0.3.dist-info/RECORD
